El_Exelio/__init__.py
El_Exelio-0.0.0.3.dist-info/METADATA
El_Exelio-0.0.0.3.dist-info/WHEEL
El_Exelio-0.0.0.3.dist-info/top_level.txt
El_Exelio-0.0.0.3.dist-info/RECORD
